.hgignore
setup.cfg
setup.py
SchevoPolicy.egg-info/PKG-INFO
SchevoPolicy.egg-info/SOURCES.txt
SchevoPolicy.egg-info/dependency_links.txt
SchevoPolicy.egg-info/entry_points.txt
SchevoPolicy.egg-info/not-zip-safe
SchevoPolicy.egg-info/paster_plugins.txt
SchevoPolicy.egg-info/requires.txt
SchevoPolicy.egg-info/top_level.txt
doc/__init__.py
doc/creating.txt
doc/overrides.txt
doc/transactions.txt
schevopolicy/__init__.py
schevopolicy/constant.py
schevopolicy/convert.py
schevopolicy/error.py
schevopolicy/policy.py
schevopolicy/rdatabase.py
schevopolicy/rentity.py
schevopolicy/rextent.py
schevopolicy/rtransaction.py
schevopolicy/schema.py
schevopolicy/wrapper.py
schevopolicy/test/__init__.py
schevopolicy/test/base.py
schevopolicy/test/test_policy_from_location.py
schevopolicy/test/test_schevo_tests.py
schevopolicy/test/test_policy/__init__.py
schevopolicy/test/test_policy/policy_001.py
schevopolicy/test/test_policy/policy_002.py
